{
  "recentFiles": [
    {
      "basename": "2025-01-21",
      "path": "logs/2025-01-21.md"
    },
    {
      "basename": "2025-01-22",
      "path": "logs/2025-01-22.md"
    },
    {
      "basename": "2025-01-31",
      "path": "logs/2025-01-31.md"
    },
    {
      "basename": "2025-01-15",
      "path": "logs/2025-01-15.md"
    },
    {
      "basename": "2025-01-18",
      "path": "logs/2025-01-18.md"
    },
    {
      "basename": "2025-01-17",
      "path": "logs/2025-01-17.md"
    },
    {
      "basename": "不讲理的乔丹太太",
      "path": "DC/不讲理的乔丹太太.md"
    },
    {
      "basename": "棋逢对手",
      "path": "DC/棋逢对手.md"
    },
    {
      "basename": "2814扇区最辣的男人",
      "path": "blob/2814扇区最辣的男人.md"
    },
    {
      "basename": "README",
      "path": "blob/README.md"
    },
    {
      "basename": "README",
      "path": "DC/README.md"
    },
    {
      "basename": "Wayne庄园的电影之夜",
      "path": "DC/Wayne庄园的电影之夜.md"
    },
    {
      "basename": "README",
      "path": "QZ/README.md"
    },
    {
      "basename": "new_README",
      "path": "_templates/new_README.md"
    },
    {
      "basename": "委托：荒宅里的鲜血",
      "path": "DC/委托：荒宅里的鲜血.md"
    },
    {
      "basename": "知了只能活一个夏天",
      "path": "QZ/知了只能活一个夏天.md"
    },
    {
      "basename": "todo",
      "path": "todo.md"
    },
    {
      "basename": "checklist",
      "path": "_templates/checklist.md"
    },
    {
      "basename": "危险性行为",
      "path": "DC/危险性行为.md"
    },
    {
      "basename": "如何追求离异飞行员",
      "path": "DC/如何追求离异飞行员.md"
    },
    {
      "basename": "龙息剑",
      "path": "DC/龙息剑.md"
    },
    {
      "basename": "一切要从蝙蝠侠决定站街那天说起",
      "path": "DC/一切要从蝙蝠侠决定站街那天说起.md"
    },
    {
      "basename": "在校园谈的当然是校园恋爱",
      "path": "DC/在校园谈的当然是校园恋爱.md"
    },
    {
      "basename": "我想见你",
      "path": "DC/我想见你.md"
    },
    {
      "basename": "蝙蝠洞里的惨案",
      "path": "DC/蝙蝠洞里的惨案.md"
    },
    {
      "basename": "下次一定",
      "path": "DC/下次一定.md"
    },
    {
      "basename": "蝙蝠侠多少钱一晚",
      "path": "DC/蝙蝠侠多少钱一晚.md"
    },
    {
      "basename": "哥谭小学亲子活动日",
      "path": "DC/哥谭小学亲子活动日.md"
    },
    {
      "basename": "海拔1658千米",
      "path": "DC/海拔1658千米.md"
    },
    {
      "basename": "七月之痒",
      "path": "DC/七月之痒.md"
    },
    {
      "basename": "黄粱",
      "path": "DC/黄粱.md"
    },
    {
      "basename": "达米安·韦恩绑架案",
      "path": "DC/达米安·韦恩绑架案.md"
    },
    {
      "basename": "副作用",
      "path": "DC/副作用.md"
    },
    {
      "basename": "重生之我在哥谭赶早高峰",
      "path": "DC/重生之我在哥谭赶早高峰.md"
    },
    {
      "basename": "与雇主约会违反职业道德",
      "path": "DC/与雇主约会违反职业道德.md"
    },
    {
      "basename": "没办法我老公都不着家的",
      "path": "DC/没办法我老公都不着家的.md"
    },
    {
      "basename": "没办法父母遗嘱要我结婚",
      "path": "DC/没办法父母遗嘱要我结婚.md"
    },
    {
      "basename": "王子钓美人鱼也会空军吗",
      "path": "DC/王子钓美人鱼也会空军吗.md"
    },
    {
      "basename": "白雪狐狸公主",
      "path": "DC/白雪狐狸公主.md"
    },
    {
      "basename": "蔓越莓伏特加",
      "path": "DC/蔓越莓伏特加.md"
    },
    {
      "basename": "星舰学院51系",
      "path": "DC/星舰学院51系.md"
    },
    {
      "basename": "没活就去咬打火机",
      "path": "DC/没活就去咬打火机.md"
    },
    {
      "basename": "肉体记忆",
      "path": "DC/肉体记忆.md"
    },
    {
      "basename": "暗恋是八个人的兵荒马乱",
      "path": "QZ/暗恋是八个人的兵荒马乱.md"
    },
    {
      "basename": "贼在太医院",
      "path": "QZ/贼在太医院.md"
    },
    {
      "basename": "明星煌煌",
      "path": "QZ/明星煌煌.md"
    },
    {
      "basename": "师娘教的",
      "path": "QZ/师娘教的.md"
    },
    {
      "basename": "new_note",
      "path": "_templates/new_note.md"
    }
  ],
  "omittedPaths": [],
  "omittedTags": [],
  "updateOn": "file-open",
  "omitBookmarks": true
}